{
  "portfolio_weights": {
    "ROK": 5.56,
    "EMR": 4.44,
    "HON": 4.44,
    "MSFT": 7.78,
    "NVDA": 7.78,
    "PLTR": 4.44,
    "CRWD": 4.44,
    "CGNX": 3.33,
    "AMAT": 4.44,
    "SNOW": 3.33,
    "SSYS": 3.33,
    "DDD": 2.22,
    "ROBO": 16.67,
    "SOXX": 11.11,
    "ESGU": 11.11,
    "ICLN": 5.56
  },
  "metrics": {
    "Portfolio": {
      "Total Return": "58.99%",
      "CAGR": "16.71%",
      "Max Drawdown": "-38.34%",
      "Sharpe Ratio": "0.59"
    },
    "QQQ": {
      "Total Return": "53.37%",
      "CAGR": "15.32%",
      "Max Drawdown": "-33.97%"
    },
    "SPY": {
      "Total Return": "47.14%",
      "CAGR": "13.74%",
      "Max Drawdown": "-24.47%"
    }
  },
  "holdings": [
    {
      "ticker": "ROK",
      "name": "Rockwell Automation, Inc.",
      "weight": "5.56%",
      "quantity": 27.35,
      "initial_price": 203.14,
      "last_price": 345.36,
      "news": "<a href=\"https://www.etfdailynews.com/2025/09/21/top-waste-management-stocks-to-watch-today-september-19th/\" target=\"_blank\">Top Waste Management Stocks To Watch Today \u2013 September 19th</a>"
    },
    {
      "ticker": "EMR",
      "name": "Emerson Electric Co.",
      "weight": "4.44%",
      "quantity": 75.09,
      "initial_price": 59.19,
      "last_price": 132.84,
      "news": "<a href=\"https://www.gov.uk/government/publications/b8-1af-european-metal-recycling-limited-environmental-permit-issued-eprcb3402mlv005\" target=\"_blank\">Notice: B8 1AF, European Metal Recycling Limited: environmental permit issued - EPR/CB3402ML/V005</a>"
    },
    {
      "ticker": "HON",
      "name": "Honeywell International Inc.",
      "weight": "4.44%",
      "quantity": 29.71,
      "initial_price": 149.62,
      "last_price": 209.0,
      "news": "<a href=\"https://www.etfdailynews.com/2025/09/20/sovran-advisors-llc-boosts-stake-in-honeywell-international-inc-hon/\" target=\"_blank\">Sovran Advisors LLC Boosts Stake in Honeywell International Inc. $HON</a>"
    },
    {
      "ticker": "MSFT",
      "name": "Microsoft Corporation",
      "weight": "7.78%",
      "quantity": 38.5,
      "initial_price": 202.0,
      "last_price": 514.45,
      "news": "<a href=\"https://www.barchart.com/story/news/34917162/a-6-3-billion-reason-to-buy-coreweave-stock-now\" target=\"_blank\">A $6.3 Billion Reason to Buy CoreWeave Stock Now</a>"
    },
    {
      "ticker": "NVDA",
      "name": "NVIDIA Corporation",
      "weight": "7.78%",
      "quantity": 576.56,
      "initial_price": 13.49,
      "last_price": 183.61,
      "news": "<a href=\"https://www.etfdailynews.com/2025/09/21/promising-metaverse-stocks-to-add-to-your-watchlist-september-19th/\" target=\"_blank\">Promising Metaverse Stocks To Add to Your Watchlist \u2013 September 19th</a>"
    },
    {
      "ticker": "PLTR",
      "name": "Palantir Technologies Inc.",
      "weight": "4.44%",
      "quantity": 467.84,
      "initial_price": 9.5,
      "last_price": 179.33,
      "news": "<a href=\"https://www.barchart.com/story/news/34609535/palantir-just-announced-a-lumen-deal-what-does-that-mean-for-pltr-stock-here\" target=\"_blank\">Palantir Just Announced a Lumen Deal. What Does That Mean for PLTR Stock Here?</a>"
    },
    {
      "ticker": "CRWD",
      "name": "CrowdStrike Holdings, Inc.",
      "weight": "4.44%",
      "quantity": 32.37,
      "initial_price": 137.32,
      "last_price": 493.14,
      "news": "<a href=\"https://www.thestreet.com/technology/wall-street-blinked-then-nvidia-made-boldest-move-with-crowdstrike\" target=\"_blank\">Wall Street blinked, then Nvidia built its boldest partnership yet</a>"
    },
    {
      "ticker": "CGNX",
      "name": "Cognex Corporation",
      "weight": "3.33%",
      "quantity": 54.05,
      "initial_price": 61.67,
      "last_price": 46.54,
      "news": "No news available"
    },
    {
      "ticker": "AMAT",
      "name": "Applied Materials, Inc.",
      "weight": "4.44%",
      "quantity": 77.92,
      "initial_price": 57.04,
      "last_price": 200.52,
      "news": "No news available"
    },
    {
      "ticker": "SNOW",
      "name": "Snowflake Inc.",
      "weight": "3.33%",
      "quantity": 13.28,
      "initial_price": 251.0,
      "last_price": 229.54,
      "news": "No news available"
    },
    {
      "ticker": "SSYS",
      "name": "Stratasys Ltd.",
      "weight": "3.33%",
      "quantity": 267.31,
      "initial_price": 12.47,
      "last_price": 10.37,
      "news": "No news available"
    },
    {
      "ticker": "DDD",
      "name": "3D Systems Corporation",
      "weight": "2.22%",
      "quantity": 452.59,
      "initial_price": 4.91,
      "last_price": 2.5,
      "news": "<a href=\"https://www.globenewswire.com/news-release/2025/08/29/3141237/0/en/Banner-Year-for-Mesoblast-With-First-FDA-Product-Approval-and-Successful-Commercial-Launch-of-Ryoncil.html\" target=\"_blank\">Banner Year for Mesoblast With First FDA Product Approval and Successful Commercial Launch of Ryoncil\u00ae</a>"
    },
    {
      "ticker": "ROBO",
      "name": "Robo Global Robotics and Automation Index ETF",
      "weight": "16.67%",
      "quantity": 349.31,
      "initial_price": 47.71,
      "last_price": 67.23,
      "news": "<a href=\"https://zycrypto.com/final-stage-rcof-token-presale-at-0-16-ends-soon-before-bitmart-launch/\" target=\"_blank\">Final Stage: RCOF Token Presale at $0.16 Ends Soon Before Bitmart Launch</a>"
    },
    {
      "ticker": "SOXX",
      "name": "iShares Semiconductor ETF",
      "weight": "11.11%",
      "quantity": 113.92,
      "initial_price": 97.53,
      "last_price": 269.83,
      "news": "<a href=\"https://siliconangle.com/2025/08/29/dave-vellantes-breaking-analysis-complete-collection/\" target=\"_blank\">Dave Vellante\u2019s Breaking Analysis: The complete collection</a>"
    },
    {
      "ticker": "ESGU",
      "name": "iShares ESG Aware MSCI USA ETF",
      "weight": "11.11%",
      "quantity": 155.38,
      "initial_price": 71.51,
      "last_price": 145.86,
      "news": "<a href=\"https://www.etfdailynews.com/2025/09/20/ishares-esg-aware-msci-usa-etf-esgu-shares-sold-by-pallas-capital-advisors-llc/\" target=\"_blank\">iShares ESG Aware MSCI USA ETF $ESGU Shares Sold by Pallas Capital Advisors LLC</a>"
    },
    {
      "ticker": "ICLN",
      "name": "iShares Global Clean Energy ETF",
      "weight": "5.56%",
      "quantity": 320.03,
      "initial_price": 17.36,
      "last_price": 15.36,
      "news": "No news available"
    }
  ],
  "last_updated": "2025-09-22T16:00:00+00:00",
  "data_date": "2025-09-22",
  "chart_path": "charts/portfolio_vs_benchmarks.png"
}